test_settings.py
test_urls.py
bank_transaction_bridge/__init__.py
bank_transaction_bridge/admin.py
bank_transaction_bridge/apps.py
bank_transaction_bridge/forms.py
bank_transaction_bridge/models.py
bank_transaction_bridge/schemas.py
bank_transaction_bridge/urls.py
bank_transaction_bridge/views.py
bank_transaction_bridge/.history/forms_20251009153758.py
bank_transaction_bridge/.history/forms_20251017175702.py
bank_transaction_bridge/convertors/file_to_json_convertor.py
bank_transaction_bridge/convertors/json_to_transactions_convertor.py
bank_transaction_bridge/migrations/0001_initial.py
bank_transaction_bridge/migrations/0002_importmapping.py
bank_transaction_bridge/migrations/0003_rename_notes_bankaccount_comment_and_more.py
bank_transaction_bridge/migrations/0004_alter_transaction_reference.py
bank_transaction_bridge/migrations/__init__.py
bank_transaction_bridge/static/bank_transaction_bridge/style.css
bank_transaction_bridge/templates/bank_transaction_bridge/bankaccount_form.html
bank_transaction_bridge/templates/bank_transaction_bridge/bankaccount_list.html
bank_transaction_bridge/templates/bank_transaction_bridge/base.html
bank_transaction_bridge/templates/bank_transaction_bridge/import_file.html
bank_transaction_bridge/templates/bank_transaction_bridge/importmapping_form.html
bank_transaction_bridge/templates/bank_transaction_bridge/importmapping_list.html
bank_transaction_bridge/templates/bank_transaction_bridge/navbar.html
bank_transaction_bridge/templates/bank_transaction_bridge/transaction_list.html
bank_transaction_bridge/templates/bank_transaction_bridge/snippets/action_inputs.html
bank_transaction_bridge/templates/bank_transaction_bridge/snippets/actions.html
bank_transaction_bridge/templates/bank_transaction_bridge/snippets/bankaccount_row.html
bank_transaction_bridge/templates/bank_transaction_bridge/snippets/bankaccount_title_row.html
bank_transaction_bridge/templates/bank_transaction_bridge/snippets/bankaccount_tooltip_buttons.html
django_bank_transaction_bridge-0.2.1.dist-info/licenses/LICENSE
django_bank_transaction_bridge-0.2.1.dist-info/METADATA
django_bank_transaction_bridge-0.2.1.dist-info/WHEEL
django_bank_transaction_bridge-0.2.1.dist-info/top_level.txt
django_bank_transaction_bridge-0.2.1.dist-info/RECORD
