Metadata-Version: 2.4
Name: django-bank-transaction-bridge
Version: 0.2.1
Summary: A Django app to manage importing bank statements.
Author-email: Alex Gorji <ag@roko.li>
License-Expression: EUPL-1.2
Project-URL: Homepage, https://gitlab.com/alexgorji/django-bank-transaction-bridge
Classifier: Environment :: Web Environment
Classifier: Framework :: Django
Classifier: Intended Audience :: Developers
Classifier: Operating System :: OS Independent
Classifier: Programming Language :: Python
Classifier: Programming Language :: Python :: 3
Classifier: Programming Language :: Python :: 3 :: Only
Classifier: Programming Language :: Python :: 3.10
Classifier: Programming Language :: Python :: 3.11
Classifier: Programming Language :: Python :: 3.12
Classifier: Programming Language :: Python :: 3.13
Classifier: Topic :: Internet :: WWW/HTTP
Classifier: Topic :: Internet :: WWW/HTTP :: Dynamic Content
Requires-Python: >=3.13
License-File: LICENSE
Requires-Dist: django>=4.2.25
Requires-Dist: django-ninja>=1.4.3
Requires-Dist: pandas>=2.3.3
Dynamic: license-file
